tej_protoc/__init__.py
tej_protoc/callbacks.py
tej_protoc/client.py
tej_protoc/exceptions.py
tej_protoc/file.py
tej_protoc/logger.py
tej_protoc/ping.py
tej_protoc/protocol.py
tej_protoc/server.py
tej_protoc/status.py
tej_protoc-0.2.4.dist-info/METADATA
tej_protoc-0.2.4.dist-info/WHEEL
tej_protoc-0.2.4.dist-info/top_level.txt
tej_protoc-0.2.4.dist-info/RECORD
