Metadata-Version: 2.1
Name: tej-protoc
Version: 0.2.4
Summary: A TEJ Protocol implementation
Home-page: https://github.com/tejmagar/tej-protoc
License: MIT
Classifier: Programming Language :: Python :: 3
Classifier: License :: OSI Approved :: MIT License
Classifier: Operating System :: OS Independent
Requires-Python: >=3.7
